MANIFEST.in
README.md
setup.py
./setup.py
./scrongo/__init__.py
./scrongo/scrongo.py
scrongo/__init__.py
scrongo/scrongo.py
scrongo.egg-info/PKG-INFO
scrongo.egg-info/SOURCES.txt
scrongo.egg-info/dependency_links.txt
scrongo.egg-info/requires.txt
scrongo.egg-info/top_level.txt
scrongo.egg-info/zip-safe