Metadata-Version: 1.0
Name: scrongo
Version: 0.0.0
Summary: Non-blocking ItemExporter for MongoDB
Home-page: https://github.com/lthibault/scrongo
Author: Louis Thibault
Author-email: l.thibault@sentimens.com
License: MIT
Keywords: scrapy,mongo,mongodb,mongo,nosql,async,nonblocking,twisted
Platform: UNKNOWN
